{
  "project_info": {
    "project_number": "265499644480",
    "firebase_url": "https://mylen-2020.firebaseio.com",
    "project_id": "mylen-2020",
    "storage_bucket": "mylen-2020.appspot.com"
  },
  "client": [
    {
      "client_info": {
        "mobilesdk_app_id": "1:265499644480:android:606541f61993e3aede05a5",
        "android_client_info": {
          "package_name": "com.example.eyeexercisetest"
        }
      },
      "oauth_client": [
        {
          "client_id": "265499644480-vdu0jbc7nu6mv38qvk88kahk5c4214rt.apps.googleusercontent.com",
          "client_type": 3
        }
      ],
      "api_key": [
        {
          "current_key": "AIzaSyCnfotLRBVt2U6VWAvya4phAWXfmk6b96c"
        }
      ],
      "services": {
        "appinvite_service": {
          "other_platform_oauth_client": [
            {
              "client_id": "265499644480-vdu0jbc7nu6mv38qvk88kahk5c4214rt.apps.googleusercontent.com",
              "client_type": 3
            }
          ]
        }
      }
    },
    {
      "client_info": {
        "mobilesdk_app_id": "1:265499644480:android:28bf2a0a601b7622de05a5",
        "android_client_info": {
          "package_name": "com.example.eyetest"
        }
      },
      "oauth_client": [
        {
          "client_id": "265499644480-aopla7aupsi0hpjpktsa8o0m3amrahj4.apps.googleusercontent.com",
          "client_type": 1,
          "android_info": {
            "package_name": "com.example.eyetest",
            "certificate_hash": "9a53167fa59d31763d7a3863632204b57f62133a"
          }
        },
        {
          "client_id": "265499644480-vdu0jbc7nu6mv38qvk88kahk5c4214rt.apps.googleusercontent.com",
          "client_type": 3
        }
      ],
      "api_key": [
        {
          "current_key": "AIzaSyCnfotLRBVt2U6VWAvya4phAWXfmk6b96c"
        }
      ],
      "services": {
        "appinvite_service": {
          "other_platform_oauth_client": [
            {
              "client_id": "265499644480-vdu0jbc7nu6mv38qvk88kahk5c4214rt.apps.googleusercontent.com",
              "client_type": 3
            }
          ]
        }
      }
    },
    {
      "client_info": {
        "mobilesdk_app_id": "1:265499644480:android:319339de5af46b3fde05a5",
        "android_client_info": {
          "package_name": "com.example.mylen"
        }
      },
      "oauth_client": [
        {
          "client_id": "265499644480-vdu0jbc7nu6mv38qvk88kahk5c4214rt.apps.googleusercontent.com",
          "client_type": 3
        }
      ],
      "api_key": [
        {
          "current_key": "AIzaSyCnfotLRBVt2U6VWAvya4phAWXfmk6b96c"
        }
      ],
      "services": {
        "appinvite_service": {
          "other_platform_oauth_client": [
            {
              "client_id": "265499644480-vdu0jbc7nu6mv38qvk88kahk5c4214rt.apps.googleusercontent.com",
              "client_type": 3
            }
          ]
        }
      }
    }
  ],
  "configuration_version": "1"
}